nanoleaf/__init__.py
nanoleaf/aurora.py
nanoleaf/setup.py
nanoleaf-0.4.1.dist-info/DESCRIPTION.rst
nanoleaf-0.4.1.dist-info/METADATA
nanoleaf-0.4.1.dist-info/RECORD
nanoleaf-0.4.1.dist-info/WHEEL
nanoleaf-0.4.1.dist-info/metadata.json
nanoleaf-0.4.1.dist-info/top_level.txt
