Metadata-Version: 2.0
Name: nanoleaf
Version: 0.4.1
Summary: Python interface for Nanoleaf Aurora.
Home-page: https://github.com/software-2/nanoleaf
Author: Anthony Bryan
Author-email: projects@anthonybryan.net
License: UNKNOWN
Download-URL: https://github.com/software-2/nanoleaf/archive/0.4.1.tar.gz
Keywords: nanoleaf,aurora,lighting,openAPI
Platform: UNKNOWN
Classifier: Topic :: Home Automation
Classifier: License :: OSI Approved :: MIT License
Classifier: Programming Language :: Python :: 3
Requires-Dist: requests
